[
  {
    "Year": "2025",
    "Student Group": "ADA 504",
    "Result (%) (All Students)": "\u2264 5.0",
    "Count": "*",
    "Total": "314",
    "county_name": "Kent County",
    "county_code": "14",
    "school_name": "Galena Elementary School",
    "school_code": "0105"
  },
  {
    "Year": "2025",
    "Student Group": "Eco Disadv",
    "Result (%) (All Students)": "49.4",
    "Count": "155",
    "Total": "314",
    "county_name": "Kent County",
    "county_code": "14",
    "school_name": "Galena Elementary School",
    "school_code": "0105"
  },
  {
    "Year": "2025",
    "Student Group": "FARMS",
    "Result (%) (All Students)": "57.6",
    "Count": "181",
    "Total": "314",
    "county_name": "Kent County",
    "county_code": "14",
    "school_name": "Galena Elementary School",
    "school_code": "0105"
  },
  {
    "Year": "2025",
    "Student Group": "ML",
    "Result (%) (All Students)": "8.0",
    "Count": "25",
    "Total": "314",
    "county_name": "Kent County",
    "county_code": "14",
    "school_name": "Galena Elementary School",
    "school_code": "0105"
  },
  {
    "Year": "2025",
    "Student Group": "Migrant",
    "Result (%) (All Students)": "*",
    "Count": "*",
    "Total": "314",
    "county_name": "Kent County",
    "county_code": "14",
    "school_name": "Galena Elementary School",
    "school_code": "0105"
  },
  {
    "Year": "2025",
    "Student Group": "SWD",
    "Result (%) (All Students)": "11.5",
    "Count": "36",
    "Total": "314",
    "county_name": "Kent County",
    "county_code": "14",
    "school_name": "Galena Elementary School",
    "school_code": "0105"
  },
  {
    "Year": "2025",
    "Student Group": "Title 1",
    "Result (%) (All Students)": "\u2265 95.0",
    "Count": "*",
    "Total": "314",
    "county_name": "Kent County",
    "county_code": "14",
    "school_name": "Galena Elementary School",
    "school_code": "0105"
  },
  {
    "Year": "2025",
    "Student Group": "ADA 504",
    "Result (%) (All Students)": "\u2264 5.0",
    "Count": "*",
    "Total": "327",
    "county_name": "Kent County",
    "county_code": "14",
    "school_name": "H. H. Garnett Elementary",
    "school_code": "0403"
  },
  {
    "Year": "2025",
    "Student Group": "Eco Disadv",
    "Result (%) (All Students)": "66.7",
    "Count": "218",
    "Total": "327",
    "county_name": "Kent County",
    "county_code": "14",
    "school_name": "H. H. Garnett Elementary",
    "school_code": "0403"
  },
  {
    "Year": "2025",
    "Student Group": "FARMS",
    "Result (%) (All Students)": "73.1",
    "Count": "239",
    "Total": "327",
    "county_name": "Kent County",
    "county_code": "14",
    "school_name": "H. H. Garnett Elementary",
    "school_code": "0403"
  },
  {
    "Year": "2025",
    "Student Group": "ML",
    "Result (%) (All Students)": "9.5",
    "Count": "31",
    "Total": "327",
    "county_name": "Kent County",
    "county_code": "14",
    "school_name": "H. H. Garnett Elementary",
    "school_code": "0403"
  },
  {
    "Year": "2025",
    "Student Group": "SWD",
    "Result (%) (All Students)": "10.7",
    "Count": "35",
    "Total": "327",
    "county_name": "Kent County",
    "county_code": "14",
    "school_name": "H. H. Garnett Elementary",
    "school_code": "0403"
  },
  {
    "Year": "2025",
    "Student Group": "Title 1",
    "Result (%) (All Students)": "\u2265 95.0",
    "Count": "*",
    "Total": "327",
    "county_name": "Kent County",
    "county_code": "14",
    "school_name": "H. H. Garnett Elementary",
    "school_code": "0403"
  },
  {
    "Year": "2025",
    "Student Group": "Homeless",
    "Result (%) (All Students)": "\u2264 5.0",
    "Count": "*",
    "Total": "327",
    "county_name": "Kent County",
    "county_code": "14",
    "school_name": "H. H. Garnett Elementary",
    "school_code": "0403"
  },
  {
    "Year": "2025",
    "Student Group": "ADA 504",
    "Result (%) (All Students)": "*",
    "Count": "*",
    "Total": "194",
    "county_name": "Kent County",
    "county_code": "14",
    "school_name": "Rock Hall Elementary",
    "school_code": "0504"
  },
  {
    "Year": "2025",
    "Student Group": "Eco Disadv",
    "Result (%) (All Students)": "67.5",
    "Count": "131",
    "Total": "194",
    "county_name": "Kent County",
    "county_code": "14",
    "school_name": "Rock Hall Elementary",
    "school_code": "0504"
  },
  {
    "Year": "2025",
    "Student Group": "FARMS",
    "Result (%) (All Students)": "75.8",
    "Count": "147",
    "Total": "194",
    "county_name": "Kent County",
    "county_code": "14",
    "school_name": "Rock Hall Elementary",
    "school_code": "0504"
  },
  {
    "Year": "2025",
    "Student Group": "ML",
    "Result (%) (All Students)": "*",
    "Count": "*",
    "Total": "194",
    "county_name": "Kent County",
    "county_code": "14",
    "school_name": "Rock Hall Elementary",
    "school_code": "0504"
  },
  {
    "Year": "2025",
    "Student Group": "SWD",
    "Result (%) (All Students)": "16.0",
    "Count": "31",
    "Total": "194",
    "county_name": "Kent County",
    "county_code": "14",
    "school_name": "Rock Hall Elementary",
    "school_code": "0504"
  },
  {
    "Year": "2025",
    "Student Group": "Title 1",
    "Result (%) (All Students)": "\u2265 95.0",
    "Count": "*",
    "Total": "194",
    "county_name": "Kent County",
    "county_code": "14",
    "school_name": "Rock Hall Elementary",
    "school_code": "0504"
  },
  {
    "Year": "2025",
    "Student Group": "Homeless",
    "Result (%) (All Students)": "7.7",
    "Count": "15",
    "Total": "194",
    "county_name": "Kent County",
    "county_code": "14",
    "school_name": "Rock Hall Elementary",
    "school_code": "0504"
  },
  {
    "Year": "2025",
    "Student Group": "ADA 504",
    "Result (%) (All Students)": "8.8",
    "Count": "32",
    "Total": "362",
    "county_name": "Kent County",
    "county_code": "14",
    "school_name": "Kent County Middle School",
    "school_code": "0402"
  },
  {
    "Year": "2025",
    "Student Group": "Eco Disadv",
    "Result (%) (All Students)": "68.2",
    "Count": "247",
    "Total": "362",
    "county_name": "Kent County",
    "county_code": "14",
    "school_name": "Kent County Middle School",
    "school_code": "0402"
  },
  {
    "Year": "2025",
    "Student Group": "FARMS",
    "Result (%) (All Students)": "74.6",
    "Count": "270",
    "Total": "362",
    "county_name": "Kent County",
    "county_code": "14",
    "school_name": "Kent County Middle School",
    "school_code": "0402"
  },
  {
    "Year": "2025",
    "Student Group": "ML",
    "Result (%) (All Students)": "7.7",
    "Count": "28",
    "Total": "362",
    "county_name": "Kent County",
    "county_code": "14",
    "school_name": "Kent County Middle School",
    "school_code": "0402"
  },
  {
    "Year": "2025",
    "Student Group": "Migrant",
    "Result (%) (All Students)": "*",
    "Count": "*",
    "Total": "362",
    "county_name": "Kent County",
    "county_code": "14",
    "school_name": "Kent County Middle School",
    "school_code": "0402"
  },
  {
    "Year": "2025",
    "Student Group": "SWD",
    "Result (%) (All Students)": "14.1",
    "Count": "51",
    "Total": "362",
    "county_name": "Kent County",
    "county_code": "14",
    "school_name": "Kent County Middle School",
    "school_code": "0402"
  },
  {
    "Year": "2025",
    "Student Group": "Title 1",
    "Result (%) (All Students)": "\u2265 95.0",
    "Count": "*",
    "Total": "362",
    "county_name": "Kent County",
    "county_code": "14",
    "school_name": "Kent County Middle School",
    "school_code": "0402"
  },
  {
    "Year": "2025",
    "Student Group": "ADA 504",
    "Result (%) (All Students)": "11.3",
    "Count": "57",
    "Total": "505",
    "county_name": "Kent County",
    "county_code": "14",
    "school_name": "Kent County High",
    "school_code": "0301"
  },
  {
    "Year": "2025",
    "Student Group": "Eco Disadv",
    "Result (%) (All Students)": "59.4",
    "Count": "300",
    "Total": "505",
    "county_name": "Kent County",
    "county_code": "14",
    "school_name": "Kent County High",
    "school_code": "0301"
  },
  {
    "Year": "2025",
    "Student Group": "FARMS",
    "Result (%) (All Students)": "62.0",
    "Count": "313",
    "Total": "505",
    "county_name": "Kent County",
    "county_code": "14",
    "school_name": "Kent County High",
    "school_code": "0301"
  },
  {
    "Year": "2025",
    "Student Group": "ML",
    "Result (%) (All Students)": "\u2264 5.0",
    "Count": "*",
    "Total": "505",
    "county_name": "Kent County",
    "county_code": "14",
    "school_name": "Kent County High",
    "school_code": "0301"
  },
  {
    "Year": "2025",
    "Student Group": "Migrant",
    "Result (%) (All Students)": "*",
    "Count": "*",
    "Total": "505",
    "county_name": "Kent County",
    "county_code": "14",
    "school_name": "Kent County High",
    "school_code": "0301"
  },
  {
    "Year": "2025",
    "Student Group": "SWD",
    "Result (%) (All Students)": "13.5",
    "Count": "68",
    "Total": "505",
    "county_name": "Kent County",
    "county_code": "14",
    "school_name": "Kent County High",
    "school_code": "0301"
  },
  {
    "Year": "2025",
    "Student Group": "Homeless",
    "Result (%) (All Students)": "\u2264 5.0",
    "Count": "*",
    "Total": "505",
    "county_name": "Kent County",
    "county_code": "14",
    "school_name": "Kent County High",
    "school_code": "0301"
  }
]